odoo/addons/partner_contact_address/__init__.py
odoo/addons/partner_contact_address/__manifest__.py
odoo/addons/partner_contact_address/models/__init__.py
odoo/addons/partner_contact_address/models/partner.py
odoo12_addon_partner_contact_address-12.0.1.0.0.99.dev3.dist-info/METADATA
odoo12_addon_partner_contact_address-12.0.1.0.0.99.dev3.dist-info/WHEEL
odoo12_addon_partner_contact_address-12.0.1.0.0.99.dev3.dist-info/top_level.txt
odoo12_addon_partner_contact_address-12.0.1.0.0.99.dev3.dist-info/RECORD
